air_link/.syncignore
air_link/__init__.py
air_link/air-link.service
air_link/authorized_keys.py
air_link/install.py
air_link/main.py
air_link/main_page.py
air_link/network.py
air_link/package.py
air_link/run.py
air_link/ssh.py
air_link/system.py
air_link/version.py
air_link-0.5.0.dist-info/LICENSE
air_link-0.5.0.dist-info/METADATA
air_link-0.5.0.dist-info/WHEEL
air_link-0.5.0.dist-info/entry_points.txt
air_link-0.5.0.dist-info/RECORD
