Metadata-Version: 2.1
Name: air-link
Version: 0.5.0
Summary: Provide SSH access, diagnostics and administration for your edge devices.
Home-page: https://github.com/zauberzeug/air-link
Author: Zauberzeug GmbH
Author-email: info@zauberzeug.com
Requires-Python: >=3.8.2,<4.0.0
Classifier: Programming Language :: Python :: 3
Classifier: Programming Language :: Python :: 3.9
Classifier: Programming Language :: Python :: 3.10
Classifier: Programming Language :: Python :: 3.11
Classifier: Programming Language :: Python :: 3.12
Requires-Dist: aioping (>=0.4.0,<0.5.0)
Requires-Dist: docker (>=7.1.0,<8.0.0)
Requires-Dist: docutils (==0.20.1)
Requires-Dist: nicegui (>=2.14.1,<3.0.0)
Project-URL: Repository, https://github.com/zauberzeug/air-link
